stackstac/.DS_Store
stackstac/__init__.py
stackstac/accumulate_metadata.py
stackstac/geom_utils.py
stackstac/nodata_reader.py
stackstac/ops.py
stackstac/prepare.py
stackstac/raster_spec.py
stackstac/reader_protocol.py
stackstac/rio_env.py
stackstac/rio_reader.py
stackstac/show.py
stackstac/stac_types.py
stackstac/stack.py
stackstac/testing/__init__.py
stackstac/testing/strategies.py
stackstac/tests/__init__.py
stackstac/tests/test_mosaic.py
stackstac/tests/test_stac_types.py
stackstac/tests/test_to_dask.py
stackstac/timer.py
stackstac/to_dask.py
stackstac-0.5.1.dist-info/WHEEL
stackstac-0.5.1.dist-info/METADATA
stackstac-0.5.1.dist-info/licenses/LICENSE
stackstac-0.5.1.dist-info/RECORD
