Metadata-Version: 2.1
Name: stackstac
Version: 0.5.1
Summary: Load a STAC collection into xarray with dask
License: MIT
Author-email: Gabe Joseph <gjoseph92@gmail.com>
Requires-Python: >=3.8,<4.0
Provides-Extra: viz
Project-URL: homepage, https://stackstac.readthedocs.io/en/latest/index.html
Project-URL: repository, https://github.com/gjoseph92/stackstac
